testjjasisnki/__init__.py
testjjasisnki/m_mod_jjasinski.py
testjjasinski-0.0.1.dist-info/License.txt
testjjasinski-0.0.1.dist-info/METADATA
testjjasinski-0.0.1.dist-info/WHEEL
testjjasinski-0.0.1.dist-info/top_level.txt
testjjasinski-0.0.1.dist-info/RECORD
