Metadata-Version: 2.1
Name: testjjasinski
Version: 0.0.1
Summary: My test package
Author-email: JJ <mail@testowy.com>
License: MIT License
Keywords: testjjasinski,name,surname
Classifier: Framework :: IDLE
Classifier: Natural Language :: Polish
Requires-Python: >=3.0
License-File: License.txt
Requires-Dist: python-version (>='3.0')
Requires-Dist: numpy
